moltopolparser/__init__.py
moltopolparser/gmx.py
moltopolparser-0.0.1a3.dist-info/LICENSE
moltopolparser-0.0.1a3.dist-info/METADATA
moltopolparser-0.0.1a3.dist-info/WHEEL
moltopolparser-0.0.1a3.dist-info/top_level.txt
moltopolparser-0.0.1a3.dist-info/RECORD
