Metadata-Version: 2.1
Name: moltopolparser
Version: 0.0.1a3
Summary: A lightweight package to parse and process molecular simulation files
Home-page: https://github.com/xinmengbcr/MolTopolParser
Author: Xinmeng Li
Author-email: xinmeng@bocores.com
License: UNKNOWN
Platform: UNKNOWN
Classifier: Programming Language :: Python :: 3
Classifier: License :: OSI Approved :: Apache Software License
Classifier: Operating System :: OS Independent
Requires-Python: >=3.6
License-File: LICENSE
Requires-Dist: pydantic >=2.7.2
Requires-Dist: numpy >=1.26.4
